pre_commit_hooks/VERSION
pre_commit_hooks/__init__.py
pre_commit_hooks/gitlab_ci_lint.py
pre_commit_hooks/gitlab_script_check.py
pre_commit_hooks/gitlab_precommit.egg-info/PKG-INFO
pre_commit_hooks/gitlab_precommit.egg-info/SOURCES.txt
pre_commit_hooks/gitlab_precommit.egg-info/dependency_links.txt
pre_commit_hooks/gitlab_precommit.egg-info/entry_points.txt
pre_commit_hooks/gitlab_precommit.egg-info/requires.txt
pre_commit_hooks/gitlab_precommit.egg-info/top_level.txt
pre_commit_hooks/shared/__init__.py
pre_commit_hooks/shared/debug_mode.py
pre_commit_hooks/shared/importer.py
gitlab_precommit-0.1.1.dist-info/LICENSE
gitlab_precommit-0.1.1.dist-info/METADATA
gitlab_precommit-0.1.1.dist-info/WHEEL
gitlab_precommit-0.1.1.dist-info/entry_points.txt
gitlab_precommit-0.1.1.dist-info/top_level.txt
gitlab_precommit-0.1.1.dist-info/RECORD
