Metadata-Version: 2.1
Name: gitlab-precommit
Version: 0.1.1
Summary: Pre-commit hooks to validate gitlab CI configuration.
Home-page: https://github.com/jacobdonenfeld/gitlab-lint-hooks
Author: Jacob Donenfeld
Author-email: jedonenfeld@gmail.com
License: MIT
Classifier: License :: OSI Approved :: MIT License
Classifier: Programming Language :: Python :: 3
Classifier: Programming Language :: Python :: 3.7
Classifier: Programming Language :: Python :: 3.8
Classifier: Programming Language :: Python :: 3.9
Classifier: Programming Language :: Python :: 3.10
Classifier: Programming Language :: Python :: Implementation :: CPython
Classifier: Programming Language :: Python :: Implementation :: PyPy
Requires-Python: >=3.7
License-File: LICENSE
Requires-Dist: lenses
Requires-Dist: PyYAML
Requires-Dist: python-gitlab
Requires-Dist: requests
Requires-Dist: GitPython
